jetsontools/__init__.py
jetsontools/__main__.py
jetsontools/_info.py
jetsontools/_log.py
jetsontools/_parsing.py
jetsontools/_tegradata.py
jetsontools/_tegrastats.py
jetsontools/py.typed
jetsontools-0.1.1.dist-info/licenses/LICENSE
jetsontools-0.1.1.dist-info/METADATA
jetsontools-0.1.1.dist-info/WHEEL
jetsontools-0.1.1.dist-info/top_level.txt
jetsontools-0.1.1.dist-info/RECORD
